bitdataset/BitDatasetAPI.py
bitdataset/BitDatasetPandas.py
bitdataset/__init__.py
bitdataset-0.1.dist-info/METADATA
bitdataset-0.1.dist-info/WHEEL
bitdataset-0.1.dist-info/top_level.txt
bitdataset-0.1.dist-info/RECORD
