Metadata-Version: 2.1
Name: bitdataset
Version: 0.1
Summary: BitDataset API connector
Home-page: http://bitdataset.com/
Author: BitDataset
Author-email: support@bitdataset.com 
License: UNKNOWN
Platform: UNKNOWN
Classifier: Programming Language :: Python :: 3
Classifier: License :: OSI Approved :: MIT License
Classifier: Operating System :: OS Independent
Requires-Dist: pandas
